{
  "id": "add6ced8-e355-4b2b-a437-6d9f0b42a5e6",
  "prevId": "00000000-0000-0000-0000-000000000000",
  "version": "7",
  "dialect": "postgresql",
  "tables": {
    "public.ai_calls": {
      "name": "ai_calls",
      "schema": "",
      "columns": {
        "id": {
          "name": "id",
          "type": "uuid",
          "primaryKey": true,
          "notNull": true,
          "default": "gen_random_uuid()"
        },
        "user_id": {
          "name": "user_id",
          "type": "uuid",
          "primaryKey": false,
          "notNull": true
        },
        "tokens_in": {
          "name": "tokens_in",
          "type": "integer",
          "primaryKey": false,
          "notNull": false
        },
        "tokens_out": {
          "name": "tokens_out",
          "type": "integer",
          "primaryKey": false,
          "notNull": false
        },
        "cost_usd": {
          "name": "cost_usd",
          "type": "numeric(10, 6)",
          "primaryKey": false,
          "notNull": false
        },
        "created_at": {
          "name": "created_at",
          "type": "timestamp with time zone",
          "primaryKey": false,
          "notNull": false,
          "default": "now()"
        }
      },
      "indexes": {},
      "foreignKeys": {
        "ai_calls_user_id_users_id_fk": {
          "name": "ai_calls_user_id_users_id_fk",
          "tableFrom": "ai_calls",
          "tableTo": "users",
          "columnsFrom": [
            "user_id"
          ],
          "columnsTo": [
            "id"
          ],
          "onDelete": "cascade",
          "onUpdate": "no action"
        }
      },
      "compositePrimaryKeys": {},
      "uniqueConstraints": {},
      "policies": {},
      "checkConstraints": {},
      "isRLSEnabled": false
    },
    "public.day_rules": {
      "name": "day_rules",
      "schema": "",
      "columns": {
        "id": {
          "name": "id",
          "type": "uuid",
          "primaryKey": true,
          "notNull": true,
          "default": "gen_random_uuid()"
        },
        "user_id": {
          "name": "user_id",
          "type": "uuid",
          "primaryKey": false,
          "notNull": true
        },
        "day_of_week": {
          "name": "day_of_week",
          "type": "integer",
          "primaryKey": false,
          "notNull": true
        },
        "focus_area": {
          "name": "focus_area",
          "type": "varchar(50)",
          "primaryKey": false,
          "notNull": true,
          "default": "'flex'"
        },
        "max_focus_hours": {
          "name": "max_focus_hours",
          "type": "integer",
          "primaryKey": false,
          "notNull": false,
          "default": 8
        }
      },
      "indexes": {},
      "foreignKeys": {
        "day_rules_user_id_users_id_fk": {
          "name": "day_rules_user_id_users_id_fk",
          "tableFrom": "day_rules",
          "tableTo": "users",
          "columnsFrom": [
            "user_id"
          ],
          "columnsTo": [
            "id"
          ],
          "onDelete": "cascade",
          "onUpdate": "no action"
        }
      },
      "compositePrimaryKeys": {},
      "uniqueConstraints": {
        "day_rules_user_day_unique": {
          "name": "day_rules_user_day_unique",
          "nullsNotDistinct": false,
          "columns": [
            "user_id",
            "day_of_week"
          ]
        }
      },
      "policies": {},
      "checkConstraints": {},
      "isRLSEnabled": false
    },
    "public.habit_completions": {
      "name": "habit_completions",
      "schema": "",
      "columns": {
        "id": {
          "name": "id",
          "type": "uuid",
          "primaryKey": true,
          "notNull": true,
          "default": "gen_random_uuid()"
        },
        "habit_id": {
          "name": "habit_id",
          "type": "uuid",
          "primaryKey": false,
          "notNull": true
        },
        "user_id": {
          "name": "user_id",
          "type": "uuid",
          "primaryKey": false,
          "notNull": true
        },
        "date": {
          "name": "date",
          "type": "date",
          "primaryKey": false,
          "notNull": true
        },
        "created_at": {
          "name": "created_at",
          "type": "timestamp with time zone",
          "primaryKey": false,
          "notNull": false,
          "default": "now()"
        }
      },
      "indexes": {
        "habit_completions_user_date_idx": {
          "name": "habit_completions_user_date_idx",
          "columns": [
            {
              "expression": "user_id",
              "isExpression": false,
              "asc": true,
              "nulls": "last"
            },
            {
              "expression": "date",
              "isExpression": false,
              "asc": true,
              "nulls": "last"
            }
          ],
          "isUnique": false,
          "concurrently": false,
          "method": "btree",
          "with": {}
        }
      },
      "foreignKeys": {
        "habit_completions_habit_id_habits_id_fk": {
          "name": "habit_completions_habit_id_habits_id_fk",
          "tableFrom": "habit_completions",
          "tableTo": "habits",
          "columnsFrom": [
            "habit_id"
          ],
          "columnsTo": [
            "id"
          ],
          "onDelete": "cascade",
          "onUpdate": "no action"
        },
        "habit_completions_user_id_users_id_fk": {
          "name": "habit_completions_user_id_users_id_fk",
          "tableFrom": "habit_completions",
          "tableTo": "users",
          "columnsFrom": [
            "user_id"
          ],
          "columnsTo": [
            "id"
          ],
          "onDelete": "cascade",
          "onUpdate": "no action"
        }
      },
      "compositePrimaryKeys": {},
      "uniqueConstraints": {
        "habit_completions_habit_date_unique": {
          "name": "habit_completions_habit_date_unique",
          "nullsNotDistinct": false,
          "columns": [
            "habit_id",
            "date"
          ]
        }
      },
      "policies": {},
      "checkConstraints": {},
      "isRLSEnabled": false
    },
    "public.habits": {
      "name": "habits",
      "schema": "",
      "columns": {
        "id": {
          "name": "id",
          "type": "uuid",
          "primaryKey": true,
          "notNull": true,
          "default": "gen_random_uuid()"
        },
        "user_id": {
          "name": "user_id",
          "type": "uuid",
          "primaryKey": false,
          "notNull": true
        },
        "name": {
          "name": "name",
          "type": "varchar(200)",
          "primaryKey": false,
          "notNull": true
        },
        "section": {
          "name": "section",
          "type": "varchar(50)",
          "primaryKey": false,
          "notNull": true
        },
        "time_of_day": {
          "name": "time_of_day",
          "type": "varchar(50)",
          "primaryKey": false,
          "notNull": false
        },
        "days_of_week": {
          "name": "days_of_week",
          "type": "integer[]",
          "primaryKey": false,
          "notNull": false,
          "default": "'{0,1,2,3,4,5,6}'::integer[]"
        },
        "active": {
          "name": "active",
          "type": "boolean",
          "primaryKey": false,
          "notNull": false,
          "default": true
        },
        "created_at": {
          "name": "created_at",
          "type": "timestamp with time zone",
          "primaryKey": false,
          "notNull": false,
          "default": "now()"
        }
      },
      "indexes": {
        "habits_user_active_idx": {
          "name": "habits_user_active_idx",
          "columns": [
            {
              "expression": "user_id",
              "isExpression": false,
              "asc": true,
              "nulls": "last"
            },
            {
              "expression": "active",
              "isExpression": false,
              "asc": true,
              "nulls": "last"
            }
          ],
          "isUnique": false,
          "concurrently": false,
          "method": "btree",
          "with": {}
        }
      },
      "foreignKeys": {
        "habits_user_id_users_id_fk": {
          "name": "habits_user_id_users_id_fk",
          "tableFrom": "habits",
          "tableTo": "users",
          "columnsFrom": [
            "user_id"
          ],
          "columnsTo": [
            "id"
          ],
          "onDelete": "cascade",
          "onUpdate": "no action"
        }
      },
      "compositePrimaryKeys": {},
      "uniqueConstraints": {},
      "policies": {},
      "checkConstraints": {},
      "isRLSEnabled": false
    },
    "public.recurring_tasks": {
      "name": "recurring_tasks",
      "schema": "",
      "columns": {
        "id": {
          "name": "id",
          "type": "uuid",
          "primaryKey": true,
          "notNull": true,
          "default": "gen_random_uuid()"
        },
        "user_id": {
          "name": "user_id",
          "type": "uuid",
          "primaryKey": false,
          "notNull": true
        },
        "title": {
          "name": "title",
          "type": "varchar(500)",
          "primaryKey": false,
          "notNull": true
        },
        "category": {
          "name": "category",
          "type": "varchar(50)",
          "primaryKey": false,
          "notNull": true
        },
        "priority": {
          "name": "priority",
          "type": "integer",
          "primaryKey": false,
          "notNull": false,
          "default": 2
        },
        "duration_minutes": {
          "name": "duration_minutes",
          "type": "integer",
          "primaryKey": false,
          "notNull": false,
          "default": 60
        },
        "scheduled_time": {
          "name": "scheduled_time",
          "type": "time",
          "primaryKey": false,
          "notNull": false
        },
        "days_of_week": {
          "name": "days_of_week",
          "type": "integer[]",
          "primaryKey": false,
          "notNull": false,
          "default": "'{0,1,2,3,4,5,6}'::integer[]"
        },
        "active": {
          "name": "active",
          "type": "boolean",
          "primaryKey": false,
          "notNull": false,
          "default": true
        },
        "until_condition": {
          "name": "until_condition",
          "type": "varchar(200)",
          "primaryKey": false,
          "notNull": false
        },
        "created_at": {
          "name": "created_at",
          "type": "timestamp with time zone",
          "primaryKey": false,
          "notNull": false,
          "default": "now()"
        }
      },
      "indexes": {},
      "foreignKeys": {
        "recurring_tasks_user_id_users_id_fk": {
          "name": "recurring_tasks_user_id_users_id_fk",
          "tableFrom": "recurring_tasks",
          "tableTo": "users",
          "columnsFrom": [
            "user_id"
          ],
          "columnsTo": [
            "id"
          ],
          "onDelete": "cascade",
          "onUpdate": "no action"
        }
      },
      "compositePrimaryKeys": {},
      "uniqueConstraints": {},
      "policies": {},
      "checkConstraints": {},
      "isRLSEnabled": false
    },
    "public.tasks": {
      "name": "tasks",
      "schema": "",
      "columns": {
        "id": {
          "name": "id",
          "type": "uuid",
          "primaryKey": true,
          "notNull": true,
          "default": "gen_random_uuid()"
        },
        "user_id": {
          "name": "user_id",
          "type": "uuid",
          "primaryKey": false,
          "notNull": true
        },
        "title": {
          "name": "title",
          "type": "varchar(500)",
          "primaryKey": false,
          "notNull": true
        },
        "description": {
          "name": "description",
          "type": "text",
          "primaryKey": false,
          "notNull": false
        },
        "category": {
          "name": "category",
          "type": "varchar(50)",
          "primaryKey": false,
          "notNull": true,
          "default": "'career'"
        },
        "status": {
          "name": "status",
          "type": "varchar(50)",
          "primaryKey": false,
          "notNull": true,
          "default": "'backlog'"
        },
        "priority": {
          "name": "priority",
          "type": "integer",
          "primaryKey": false,
          "notNull": true,
          "default": 2
        },
        "assigned_day": {
          "name": "assigned_day",
          "type": "date",
          "primaryKey": false,
          "notNull": false
        },
        "scheduled_time": {
          "name": "scheduled_time",
          "type": "time",
          "primaryKey": false,
          "notNull": false
        },
        "duration_minutes": {
          "name": "duration_minutes",
          "type": "integer",
          "primaryKey": false,
          "notNull": false,
          "default": 60
        },
        "time_logged_minutes": {
          "name": "time_logged_minutes",
          "type": "integer",
          "primaryKey": false,
          "notNull": false,
          "default": 0
        },
        "last_left_off": {
          "name": "last_left_off",
          "type": "text",
          "primaryKey": false,
          "notNull": false
        },
        "next_steps": {
          "name": "next_steps",
          "type": "jsonb",
          "primaryKey": false,
          "notNull": false,
          "default": "'[]'::jsonb"
        },
        "notes": {
          "name": "notes",
          "type": "text",
          "primaryKey": false,
          "notNull": false
        },
        "created_at": {
          "name": "created_at",
          "type": "timestamp with time zone",
          "primaryKey": false,
          "notNull": false,
          "default": "now()"
        },
        "updated_at": {
          "name": "updated_at",
          "type": "timestamp with time zone",
          "primaryKey": false,
          "notNull": false,
          "default": "now()"
        }
      },
      "indexes": {
        "tasks_user_status_idx": {
          "name": "tasks_user_status_idx",
          "columns": [
            {
              "expression": "user_id",
              "isExpression": false,
              "asc": true,
              "nulls": "last"
            },
            {
              "expression": "status",
              "isExpression": false,
              "asc": true,
              "nulls": "last"
            }
          ],
          "isUnique": false,
          "concurrently": false,
          "method": "btree",
          "with": {}
        },
        "tasks_user_day_idx": {
          "name": "tasks_user_day_idx",
          "columns": [
            {
              "expression": "user_id",
              "isExpression": false,
              "asc": true,
              "nulls": "last"
            },
            {
              "expression": "assigned_day",
              "isExpression": false,
              "asc": true,
              "nulls": "last"
            }
          ],
          "isUnique": false,
          "concurrently": false,
          "method": "btree",
          "with": {}
        },
        "tasks_user_category_idx": {
          "name": "tasks_user_category_idx",
          "columns": [
            {
              "expression": "user_id",
              "isExpression": false,
              "asc": true,
              "nulls": "last"
            },
            {
              "expression": "category",
              "isExpression": false,
              "asc": true,
              "nulls": "last"
            }
          ],
          "isUnique": false,
          "concurrently": false,
          "method": "btree",
          "with": {}
        }
      },
      "foreignKeys": {
        "tasks_user_id_users_id_fk": {
          "name": "tasks_user_id_users_id_fk",
          "tableFrom": "tasks",
          "tableTo": "users",
          "columnsFrom": [
            "user_id"
          ],
          "columnsTo": [
            "id"
          ],
          "onDelete": "cascade",
          "onUpdate": "no action"
        }
      },
      "compositePrimaryKeys": {},
      "uniqueConstraints": {},
      "policies": {},
      "checkConstraints": {},
      "isRLSEnabled": false
    },
    "public.users": {
      "name": "users",
      "schema": "",
      "columns": {
        "id": {
          "name": "id",
          "type": "uuid",
          "primaryKey": true,
          "notNull": true,
          "default": "gen_random_uuid()"
        },
        "email": {
          "name": "email",
          "type": "varchar(255)",
          "primaryKey": false,
          "notNull": true
        },
        "password_hash": {
          "name": "password_hash",
          "type": "text",
          "primaryKey": false,
          "notNull": true
        },
        "name": {
          "name": "name",
          "type": "varchar(120)",
          "primaryKey": false,
          "notNull": false
        },
        "created_at": {
          "name": "created_at",
          "type": "timestamp with time zone",
          "primaryKey": false,
          "notNull": false,
          "default": "now()"
        }
      },
      "indexes": {},
      "foreignKeys": {},
      "compositePrimaryKeys": {},
      "uniqueConstraints": {
        "users_email_unique": {
          "name": "users_email_unique",
          "nullsNotDistinct": false,
          "columns": [
            "email"
          ]
        }
      },
      "policies": {},
      "checkConstraints": {},
      "isRLSEnabled": false
    }
  },
  "enums": {},
  "schemas": {},
  "sequences": {},
  "roles": {},
  "policies": {},
  "views": {},
  "_meta": {
    "columns": {},
    "schemas": {},
    "tables": {}
  }
}